stashapi/classes.py
stashapi/log.py
stashapi/marker_parse.py
stashapi/scrape_parser.py
stashapi/stash_types.py
stashapi/stashapp.py
stashapi/stashbox.py
stashapi/tools.py
stashapp_tools-0.2.59.dist-info/LICENSE
stashapp_tools-0.2.59.dist-info/METADATA
stashapp_tools-0.2.59.dist-info/WHEEL
stashapp_tools-0.2.59.dist-info/top_level.txt
stashapp_tools-0.2.59.dist-info/RECORD
