Metadata-Version: 2.1
Name: stashapp-tools
Version: 0.2.59
Summary: A python library for interfacing with a stashapp's API
Home-page: https://github.com/stg-annon/stashapp-tools
Author: stg-annon
Author-email: 14135675+stg-annon@users.noreply.github.com
License: MIT
Platform: UNKNOWN
Classifier: License :: OSI Approved :: MIT License
Classifier: Programming Language :: Python :: 3
Classifier: Programming Language :: Python :: 3.10
Requires-Dist: requests
